LICENSE.txt
README.md
setup.cfg
setup.py
tepgaast.egg-info/PKG-INFO
tepgaast.egg-info/SOURCES.txt
tepgaast.egg-info/dependency_links.txt
tepgaast.egg-info/requires.txt
tepgaast.egg-info/top_level.txt
tepgacast/__init__.py
tepgacast/tepgacast.py