Metadata-Version: 2.1
Name: tepgaast
Version: 0.1
Summary: TYPE YOUR DESCRIPTION HERE
Home-page: https://github.com/usereight8/tepgacast
Download-URL: https://github.com/usereight8/tepgacast/archive/refs/tags/0.1.tar.gz
Author: PK Varotsos
Author-email: panvar@phys.uoa.gr
License: MIT
Keywords: SOME,MEANINGFULL,KEYWORDS
Classifier: Development Status :: 3 - Alpha
Classifier: Intended Audience :: Developers
Classifier: Topic :: Software Development :: Build Tools
Classifier: License :: OSI Approved :: MIT License
Classifier: Programming Language :: Python :: 3
Classifier: Programming Language :: Python :: 3.4
Classifier: Programming Language :: Python :: 3.5
Classifier: Programming Language :: Python :: 3.6
License-File: LICENSE.txt
